fonzie/__init__.py
fonzie/apps.py
fonzie/models.py
fonzie/urls/__init__.py
fonzie/urls/acl.py
fonzie/urls/lms_root.py
fonzie/urls/status.py
fonzie/urls/user.py
fonzie/views/__init__.py
fonzie/views/acl.py
fonzie/views/status.py
fonzie/views/user.py
tests/views/__init__.py
tests/views/test_acl.py
tests/views/test_status.py
tests/views/test_user.py
tests/views/test_versioning.py
fonzie-0.7.0.dist-info/AUTHORS
fonzie-0.7.0.dist-info/LICENSE.txt
fonzie-0.7.0.dist-info/METADATA
fonzie-0.7.0.dist-info/WHEEL
fonzie-0.7.0.dist-info/top_level.txt
fonzie-0.7.0.dist-info/RECORD
