Metadata-Version: 2.1
Name: fonzie
Version: 0.7.0
Summary: A FUN API for Open edX
Home-page: https://github.com/openfun/fonzie
Author: Open FUN (France Universite Numerique)
Author-email: fun.dev@fun-mooc.fr
License: AGPL 3.0
Keywords: Django,Django Rest Framework,API,Open edX
Platform: UNKNOWN
Classifier: Development Status :: 4 - Beta
Classifier: Framework :: Django
Classifier: Framework :: Django :: 1.8
Classifier: Intended Audience :: Developers
Classifier: License :: OSI Approved :: GNU Affero General Public License v3 or later (AGPLv3+)
Classifier: Natural Language :: English
Classifier: Programming Language :: Python :: 2
Classifier: Programming Language :: Python :: 2.7
Requires-Dist: djangorestframework-simplejwt
Provides-Extra: ci
Requires-Dist: codecov (==2.1.13) ; extra == 'ci'
Requires-Dist: sphinx (==1.8.5) ; extra == 'ci'
Requires-Dist: twine (==1.15.0) ; extra == 'ci'
Provides-Extra: dev
Requires-Dist: diff-cover (==4.0.0) ; extra == 'dev'
Requires-Dist: edx-lint (==1.4.1) ; extra == 'dev'
Requires-Dist: edx-i18n-tools (==0.4.5) ; extra == 'dev'
Requires-Dist: twine (==1.15.0) ; extra == 'dev'
Requires-Dist: wheel ; extra == 'dev'
Provides-Extra: doc
Requires-Dist: doc8 (==0.8.1) ; extra == 'doc'
Requires-Dist: edx-sphinx-theme (==1.6.1) ; extra == 'doc'
Requires-Dist: readme-renderer (==28.0) ; extra == 'doc'
Requires-Dist: Sphinx (==1.8.5) ; extra == 'doc'
Provides-Extra: quality
Requires-Dist: bandit (==1.6.2) ; extra == 'quality'
Requires-Dist: caniusepython3 (==7.3.0) ; extra == 'quality'
Requires-Dist: edx-lint (==1.4.1) ; extra == 'quality'
Requires-Dist: isort (==4.3.21) ; extra == 'quality'
Requires-Dist: pycodestyle (==2.6.0) ; extra == 'quality'
Requires-Dist: pydocstyle (==3.0.0) ; extra == 'quality'
Requires-Dist: pyroma (==2.6) ; extra == 'quality'
Provides-Extra: test
Requires-Dist: factory-boy (==2.12.0) ; extra == 'test'
Requires-Dist: nose (==1.3.7) ; extra == 'test'
Requires-Dist: pytest (==4.6.11) ; extra == 'test'
Requires-Dist: pytest-cov (==2.11.1) ; extra == 'test'
Requires-Dist: pytest-django (==3.10.0) ; extra == 'test'
Requires-Dist: requests (==2.9.1) ; extra == 'test'
